maranet/__init__.py
maranet/constants.py
maranet-1.0.6.dist-info/DESCRIPTION.rst
maranet-1.0.6.dist-info/METADATA
maranet-1.0.6.dist-info/RECORD
maranet-1.0.6.dist-info/WHEEL
maranet-1.0.6.dist-info/entry_points.txt
maranet-1.0.6.dist-info/metadata.json
maranet-1.0.6.dist-info/top_level.txt
