Metadata-Version: 2.0
Name: maranet
Version: 1.0.6
Summary: A Python client library for MARA protocol. Includes server emulator, although MARA servers are tipically microcontrollers.
Home-page: https://github.com/D3f0/maranet
Author: Nahuel Defossé
Author-email: ndefosse@tw.unp.edu.ar
License: MIT license
Keywords: maranet
Platform: UNKNOWN
Classifier: Development Status :: 2 - Pre-Alpha
Classifier: Intended Audience :: Developers
Classifier: License :: OSI Approved :: MIT License
Classifier: Natural Language :: English
Classifier: Programming Language :: Python :: 2
Classifier: Programming Language :: Python :: 2.7
Classifier: Programming Language :: Python :: 3
Classifier: Programming Language :: Python :: 3.5
Classifier: Programming Language :: Python :: 3.6
Requires-Dist: Click (>=6.0)
Requires-Dist: construct (<=2.5.0)
Requires-Dist: jinja2
Requires-Dist: twisted
